odoo8_addon_partner_external_maps-8.0.0.1.0.99.dev17-py3.8-nspkg.pth
odoo_addons/partner_external_maps/README.rst
odoo_addons/partner_external_maps/__init__.py
odoo_addons/partner_external_maps/__openerp__.py
odoo_addons/partner_external_maps/map_website_data.xml
odoo_addons/partner_external_maps/map_website_view.xml
odoo_addons/partner_external_maps/partner_external_maps.py
odoo_addons/partner_external_maps/partner_view.xml
odoo_addons/partner_external_maps/post_install.py
odoo_addons/partner_external_maps/users_view.xml
odoo_addons/partner_external_maps/i18n/da.po
odoo_addons/partner_external_maps/i18n/de.po
odoo_addons/partner_external_maps/i18n/es.po
odoo_addons/partner_external_maps/i18n/eu.po
odoo_addons/partner_external_maps/i18n/fi.po
odoo_addons/partner_external_maps/i18n/fr.po
odoo_addons/partner_external_maps/i18n/it.po
odoo_addons/partner_external_maps/i18n/nl.po
odoo_addons/partner_external_maps/i18n/partner_external_maps.pot
odoo_addons/partner_external_maps/i18n/sl.po
odoo_addons/partner_external_maps/security/ir.model.access.csv
odoo_addons/partner_external_maps/static/description/icon.png
odoo8_addon_partner_external_maps-8.0.0.1.0.99.dev17.dist-info/METADATA
odoo8_addon_partner_external_maps-8.0.0.1.0.99.dev17.dist-info/WHEEL
odoo8_addon_partner_external_maps-8.0.0.1.0.99.dev17.dist-info/namespace_packages.txt
odoo8_addon_partner_external_maps-8.0.0.1.0.99.dev17.dist-info/top_level.txt
odoo8_addon_partner_external_maps-8.0.0.1.0.99.dev17.dist-info/RECORD
